pygkquiz/IQuiz.py
pygkquiz/__init__.py
pygkquiz-1.2.dist-info/LICENSE
pygkquiz-1.2.dist-info/METADATA
pygkquiz-1.2.dist-info/WHEEL
pygkquiz-1.2.dist-info/top_level.txt
pygkquiz-1.2.dist-info/RECORD
