Metadata-Version: 2.1
Name: pygkquiz
Version: 1.2
Summary: UNKNOWN
Home-page: UNKNOWN
Author: Ashok Kumar
Author-email: ashbhati2@gmail.com
License: UNKNOWN
Platform: UNKNOWN
